{
 "cells": [
  {
   "cell_type": "markdown",
   "metadata": {},
   "source": [
    "- 表达式(expression): 由标识符、字面量和操作符组成。其完成运算、属性访问以及函数运算等。表达式像数学公式总是返回一个结果\n",
    "- 语句(statement): 由一到多行代码组成，其着重于逻辑过程，完成变量赋值、类型定义以及控制执行流方向等\n",
    "- 表达式完成计算，语句执行逻辑。表达式是语句的一种，语句不一定是表达式\n",
    "- eval执行表达式，exec执行语句"
   ]
  },
  {
   "cell_type": "code",
   "execution_count": 5,
   "metadata": {},
   "outputs": [
    {
     "name": "stdout",
     "output_type": "stream",
     "text": [
      "0\n",
      "['/usr/local/lib/python3.6/site-packages/ipykernel_launcher.py', '-f', '/Users/hejl/Library/Jupyter/runtime/kernel-0f0cd9f4-73d1-47e8-8aa0-d51b94bed111.json']\n"
     ]
    }
   ],
   "source": [
    "import sys\n",
    "print(sys.flags.optimize) # 解释器参数\n",
    "print(sys.argv) # 程序启动参数"
   ]
  },
  {
   "cell_type": "markdown",
   "metadata": {},
   "source": [
    "- 终止进程的正确做法是调用sys.exit函数，它确保推出前会执行相关清理操作\n",
    "- 常见的清理操作包括finally和atexit。前者是结构化异常子句，无论异常是否发生都会执行。后者用于注册进程退出前才执行的清理函数\n",
    "- 终止进程应返回退出状态码（exit status），便于命令行工具据此做判断。返回0表示正常结束。"
   ]
  },
  {
   "cell_type": "code",
   "execution_count": 2,
   "metadata": {},
   "outputs": [
    {
     "name": "stdout",
     "output_type": "stream",
     "text": [
      "finalss\n"
     ]
    }
   ],
   "source": [
    "import atexit\n",
    "# 这里交互式环境和命令行执行结果不同，原书在命令行执行的\n",
    "atexit.register(print, 'haha')\n",
    "try:\n",
    "    exit\n",
    "finally:\n",
    "    print('finalss')"
   ]
  },
  {
   "cell_type": "code",
   "execution_count": 9,
   "metadata": {},
   "outputs": [
    {
     "name": "stdout",
     "output_type": "stream",
     "text": [
      "haha\n",
      "haha\n"
     ]
    }
   ],
   "source": [
    "exit"
   ]
  },
  {
   "cell_type": "markdown",
   "metadata": {},
   "source": [
    "- 帮助信息不同于注释，注释会被编译器忽略，帮助属于基本元数据，可在运行期查询和输出\n",
    "- 帮助信息保存在\\_\\_doc__属性中，可通过help()方法查看\n",
    "- 解释器以\"OO\"方式运行时，帮助信息会被移除"
   ]
  },
  {
   "cell_type": "markdown",
   "metadata": {},
   "source": [
    "对于三个以内的变量交换，编译器会优化为ROT指令，直接交换栈帧内数据，而不是构建元组。"
   ]
  },
  {
   "cell_type": "code",
   "execution_count": 23,
   "metadata": {},
   "outputs": [
    {
     "name": "stdout",
     "output_type": "stream",
     "text": [
      "  1           0 LOAD_NAME                0 (c)\n",
      "              2 LOAD_NAME                1 (b)\n",
      "              4 LOAD_NAME                2 (a)\n",
      "              6 ROT_THREE\n",
      "              8 ROT_TWO\n",
      "             10 STORE_NAME               2 (a)\n",
      "             12 STORE_NAME               1 (b)\n",
      "             14 STORE_NAME               0 (c)\n",
      "             16 LOAD_CONST               0 (None)\n",
      "             18 RETURN_VALUE\n"
     ]
    }
   ],
   "source": [
    "import dis\n",
    "dis.dis(compile(\"a,b,c = c,b,a\", \"\", \"exec\"))"
   ]
  },
  {
   "cell_type": "code",
   "execution_count": 4,
   "metadata": {},
   "outputs": [
    {
     "name": "stdout",
     "output_type": "stream",
     "text": [
      "  1           0 LOAD_NAME                0 (d)\n",
      "              2 LOAD_NAME                1 (c)\n",
      "              4 LOAD_NAME                2 (b)\n",
      "              6 LOAD_NAME                3 (a)\n",
      "              8 BUILD_TUPLE              4\n",
      "             10 UNPACK_SEQUENCE          4\n",
      "             12 STORE_NAME               3 (a)\n",
      "             14 STORE_NAME               2 (b)\n",
      "             16 STORE_NAME               1 (c)\n",
      "             18 STORE_NAME               0 (d)\n",
      "             20 LOAD_CONST               0 (None)\n",
      "             22 RETURN_VALUE\n"
     ]
    }
   ],
   "source": [
    "dis.dis(compile(\"a,b,c,d = d,c,b,a\", \"\", \"exec\"))"
   ]
  },
  {
   "cell_type": "markdown",
   "metadata": {},
   "source": [
    "星号收集不能单独出现，要么与其他名字一起，要么放入列表或元组内。"
   ]
  },
  {
   "cell_type": "code",
   "execution_count": 9,
   "metadata": {},
   "outputs": [
    {
     "name": "stdout",
     "output_type": "stream",
     "text": [
      "1 [] 2\n"
     ]
    }
   ],
   "source": [
    "a, *b, c = 1,2\n",
    "print(a,b,c)"
   ]
  },
  {
   "cell_type": "code",
   "execution_count": 7,
   "metadata": {},
   "outputs": [
    {
     "ename": "ValueError",
     "evalue": "not enough values to unpack (expected at least 3, got 2)",
     "output_type": "error",
     "traceback": [
      "\u001b[0;31m---------------------------------------------------------------------------\u001b[0m",
      "\u001b[0;31mValueError\u001b[0m                                Traceback (most recent call last)",
      "\u001b[0;32m<ipython-input-7-b8d595448dd4>\u001b[0m in \u001b[0;36m<module>\u001b[0;34m()\u001b[0m\n\u001b[0;32m----> 1\u001b[0;31m \u001b[0ma\u001b[0m\u001b[0;34m,\u001b[0m \u001b[0;34m*\u001b[0m\u001b[0mb\u001b[0m\u001b[0;34m,\u001b[0m \u001b[0mc\u001b[0m\u001b[0;34m,\u001b[0m \u001b[0md\u001b[0m \u001b[0;34m=\u001b[0m \u001b[0;36m1\u001b[0m\u001b[0;34m,\u001b[0m\u001b[0;36m2\u001b[0m\u001b[0;34m\u001b[0m\u001b[0m\n\u001b[0m",
      "\u001b[0;31mValueError\u001b[0m: not enough values to unpack (expected at least 3, got 2)"
     ]
    }
   ],
   "source": [
    "a, *b, c, d = 1,2"
   ]
  },
  {
   "cell_type": "code",
   "execution_count": 8,
   "metadata": {},
   "outputs": [
    {
     "ename": "SyntaxError",
     "evalue": "two starred expressions in assignment (<ipython-input-8-d74a602f44df>, line 1)",
     "output_type": "error",
     "traceback": [
      "\u001b[0;36m  File \u001b[0;32m\"<ipython-input-8-d74a602f44df>\"\u001b[0;36m, line \u001b[0;32m1\u001b[0m\n\u001b[0;31m    a, *b, *c, d = range(10)\u001b[0m\n\u001b[0m                            ^\u001b[0m\n\u001b[0;31mSyntaxError\u001b[0m\u001b[0;31m:\u001b[0m two starred expressions in assignment\n"
     ]
    }
   ],
   "source": [
    "a, *b, *c, d = range(10)"
   ]
  },
  {
   "cell_type": "code",
   "execution_count": 10,
   "metadata": {},
   "outputs": [
    {
     "ename": "SyntaxError",
     "evalue": "starred assignment target must be in a list or tuple (<ipython-input-10-441a4f01e6b3>, line 1)",
     "output_type": "error",
     "traceback": [
      "\u001b[0;36m  File \u001b[0;32m\"<ipython-input-10-441a4f01e6b3>\"\u001b[0;36m, line \u001b[0;32m1\u001b[0m\n\u001b[0;31m    *a = 1,2\u001b[0m\n\u001b[0m            ^\u001b[0m\n\u001b[0;31mSyntaxError\u001b[0m\u001b[0;31m:\u001b[0m starred assignment target must be in a list or tuple\n"
     ]
    }
   ],
   "source": [
    "*a = 1,2"
   ]
  },
  {
   "cell_type": "code",
   "execution_count": 12,
   "metadata": {},
   "outputs": [
    {
     "data": {
      "text/plain": [
       "[1, 2]"
      ]
     },
     "execution_count": 12,
     "metadata": {},
     "output_type": "execute_result"
    }
   ],
   "source": [
    "[*a] = 1,2\n",
    "a"
   ]
  },
  {
   "cell_type": "code",
   "execution_count": 15,
   "metadata": {},
   "outputs": [
    {
     "data": {
      "text/plain": [
       "[1, 2]"
      ]
     },
     "execution_count": 15,
     "metadata": {},
     "output_type": "execute_result"
    }
   ],
   "source": [
    "(*a,) = 1,2\n",
    "a"
   ]
  },
  {
   "cell_type": "code",
   "execution_count": 16,
   "metadata": {},
   "outputs": [
    {
     "ename": "SyntaxError",
     "evalue": "can't use starred expression here (<ipython-input-16-57adc70a3556>, line 2)",
     "output_type": "error",
     "traceback": [
      "\u001b[0;36m  File \u001b[0;32m\"<ipython-input-16-57adc70a3556>\"\u001b[0;36m, line \u001b[0;32m2\u001b[0m\n\u001b[0;31m    *a\u001b[0m\n\u001b[0m      ^\u001b[0m\n\u001b[0;31mSyntaxError\u001b[0m\u001b[0;31m:\u001b[0m can't use starred expression here\n"
     ]
    }
   ],
   "source": [
    "a = (1,2)\n",
    "*a"
   ]
  },
  {
   "cell_type": "code",
   "execution_count": 17,
   "metadata": {},
   "outputs": [
    {
     "data": {
      "text/plain": [
       "[1, 2]"
      ]
     },
     "execution_count": 17,
     "metadata": {},
     "output_type": "execute_result"
    }
   ],
   "source": [
    "[*a]"
   ]
  },
  {
   "cell_type": "markdown",
   "metadata": {},
   "source": [
    "链式比较减少了载入指令，更多基于栈数据复制和交换，会稍稍提升性能，更多的是提升可读性。"
   ]
  },
  {
   "cell_type": "code",
   "execution_count": 25,
   "metadata": {},
   "outputs": [
    {
     "name": "stdout",
     "output_type": "stream",
     "text": [
      "  1           0 LOAD_CONST               0 (1)\n",
      "              2 LOAD_NAME                0 (a)\n",
      "              4 DUP_TOP\n",
      "              6 ROT_THREE\n",
      "              8 COMPARE_OP               0 (<)\n",
      "             10 JUMP_IF_FALSE_OR_POP    18\n",
      "             12 LOAD_CONST               1 (2)\n",
      "             14 COMPARE_OP               0 (<)\n",
      "             16 RETURN_VALUE\n",
      "        >>   18 ROT_TWO\n",
      "             20 POP_TOP\n",
      "             22 RETURN_VALUE\n"
     ]
    }
   ],
   "source": [
    "dis.dis(compile(\"1<a<2\", '', 'eval'))"
   ]
  },
  {
   "cell_type": "code",
   "execution_count": 24,
   "metadata": {},
   "outputs": [
    {
     "name": "stdout",
     "output_type": "stream",
     "text": [
      "  1           0 LOAD_CONST               0 (1)\n",
      "              2 LOAD_NAME                0 (a)\n",
      "              4 COMPARE_OP               0 (<)\n",
      "              6 JUMP_IF_FALSE_OR_POP    14\n",
      "              8 LOAD_NAME                0 (a)\n",
      "             10 LOAD_CONST               1 (2)\n",
      "             12 COMPARE_OP               0 (<)\n",
      "        >>   14 RETURN_VALUE\n"
     ]
    }
   ],
   "source": [
    "dis.dis(compile(\"1<a and a<2\", '', 'eval'))"
   ]
  },
  {
   "cell_type": "code",
   "execution_count": 30,
   "metadata": {},
   "outputs": [
    {
     "name": "stdout",
     "output_type": "stream",
     "text": [
      "[0, 1, 2, 3, 4, 5, 6, 7, 8, 9]\n",
      "[0, 1, 2, 5, 6, 7, 8, 9]\n",
      "[0, 1, 1]\n"
     ]
    }
   ],
   "source": [
    "a = list(range(10))\n",
    "b = a[3:5]\n",
    "del b\n",
    "print(a)\n",
    "del a[3:5]\n",
    "print(a)\n",
    "a[2:8] =[1,]\n",
    "print(a)"
   ]
  },
  {
   "cell_type": "markdown",
   "metadata": {},
   "source": [
    "and返回最后，或导致短路的操作数。or返回第一真值，或最后的操作数。"
   ]
  },
  {
   "cell_type": "code",
   "execution_count": 32,
   "metadata": {},
   "outputs": [
    {
     "data": {
      "text/plain": [
       "3"
      ]
     },
     "execution_count": 32,
     "metadata": {},
     "output_type": "execute_result"
    }
   ],
   "source": [
    "1 and 2 and 3"
   ]
  },
  {
   "cell_type": "code",
   "execution_count": 33,
   "metadata": {},
   "outputs": [
    {
     "data": {
      "text/plain": [
       "0"
      ]
     },
     "execution_count": 33,
     "metadata": {},
     "output_type": "execute_result"
    }
   ],
   "source": [
    "1 and 2 and 0"
   ]
  },
  {
   "cell_type": "code",
   "execution_count": 34,
   "metadata": {},
   "outputs": [
    {
     "data": {
      "text/plain": [
       "1"
      ]
     },
     "execution_count": 34,
     "metadata": {},
     "output_type": "execute_result"
    }
   ],
   "source": [
    "0 or 1 or 2"
   ]
  },
  {
   "cell_type": "code",
   "execution_count": 35,
   "metadata": {},
   "outputs": [
    {
     "data": {
      "text/plain": [
       "[]"
      ]
     },
     "execution_count": 35,
     "metadata": {},
     "output_type": "execute_result"
    }
   ],
   "source": [
    "0 or '' or [] "
   ]
  },
  {
   "cell_type": "code",
   "execution_count": 36,
   "metadata": {},
   "outputs": [
    {
     "data": {
      "text/plain": [
       "'T'"
      ]
     },
     "execution_count": 36,
     "metadata": {},
     "output_type": "execute_result"
    }
   ],
   "source": [
    "\"T\" if 2 > 1 else \"F\""
   ]
  },
  {
   "cell_type": "code",
   "execution_count": 37,
   "metadata": {},
   "outputs": [
    {
     "data": {
      "text/plain": [
       "'T'"
      ]
     },
     "execution_count": 37,
     "metadata": {},
     "output_type": "execute_result"
    }
   ],
   "source": [
    "2 > 1 and \"T\" or \"F\""
   ]
  },
  {
   "cell_type": "code",
   "execution_count": 40,
   "metadata": {},
   "outputs": [
    {
     "data": {
      "text/plain": [
       "'F'"
      ]
     },
     "execution_count": 40,
     "metadata": {},
     "output_type": "execute_result"
    }
   ],
   "source": [
    "2 > 1 and \"\" or \"F\" # 有缺陷的情况"
   ]
  },
  {
   "cell_type": "code",
   "execution_count": 39,
   "metadata": {},
   "outputs": [
    {
     "data": {
      "text/plain": [
       "''"
      ]
     },
     "execution_count": 39,
     "metadata": {},
     "output_type": "execute_result"
    }
   ],
   "source": [
    "\"\" if 2 > 1 else \"F\""
   ]
  },
  {
   "cell_type": "code",
   "execution_count": null,
   "metadata": {},
   "outputs": [],
   "source": []
  }
 ],
 "metadata": {
  "kernelspec": {
   "display_name": "Python 3",
   "language": "python",
   "name": "python3"
  },
  "language_info": {
   "codemirror_mode": {
    "name": "ipython",
    "version": 3
   },
   "file_extension": ".py",
   "mimetype": "text/x-python",
   "name": "python",
   "nbconvert_exporter": "python",
   "pygments_lexer": "ipython3",
   "version": "3.6.5"
  }
 },
 "nbformat": 4,
 "nbformat_minor": 2
}
