{
 "cells": [
  {
   "cell_type": "markdown",
   "metadata": {},
   "source": [
    "函数由两部分组成：代码对象（func.\\_\\_code__）持有字节码和指令元数据，负责执行；函数对象则为上下文提供调用实例，并管理所需的状态数据。"
   ]
  },
  {
   "cell_type": "code",
   "execution_count": 6,
   "metadata": {},
   "outputs": [
    {
     "name": "stdout",
     "output_type": "stream",
     "text": [
      "  4           0 LOAD_FAST                0 (x)\n",
      "              2 LOAD_FAST                1 (y)\n",
      "              4 INPLACE_ADD\n",
      "              6 STORE_FAST               0 (x)\n",
      "\n",
      "  5           8 LOAD_GLOBAL              0 (print)\n",
      "             10 LOAD_FAST                0 (x)\n",
      "             12 LOAD_FAST                1 (y)\n",
      "             14 CALL_FUNCTION            2\n",
      "             16 POP_TOP\n",
      "             18 LOAD_CONST               0 (None)\n",
      "             20 RETURN_VALUE\n"
     ]
    }
   ],
   "source": [
    "import dis\n",
    "\n",
    "def test(x, y=10):\n",
    "    x += y\n",
    "    print(x,y)\n",
    "dis.dis(test)"
   ]
  },
  {
   "cell_type": "code",
   "execution_count": 8,
   "metadata": {},
   "outputs": [
    {
     "name": "stdout",
     "output_type": "stream",
     "text": [
      "          0 LOAD_FAST                0 (0)\n",
      "          2 LOAD_FAST                1 (1)\n",
      "          4 INPLACE_ADD\n",
      "          6 STORE_FAST               0 (0)\n",
      "          8 LOAD_GLOBAL              0 (0)\n",
      "         10 LOAD_FAST                0 (0)\n",
      "         12 LOAD_FAST                1 (1)\n",
      "         14 CALL_FUNCTION            2\n",
      "         16 POP_TOP\n",
      "         18 LOAD_CONST               0 (0)\n",
      "         20 RETURN_VALUE\n"
     ]
    }
   ],
   "source": [
    "dis.dis(test.__code__.co_code) # 没有元数据符号的反汇编结果"
   ]
  },
  {
   "cell_type": "code",
   "execution_count": 9,
   "metadata": {},
   "outputs": [
    {
     "data": {
      "text/plain": [
       "(10,)"
      ]
     },
     "execution_count": 9,
     "metadata": {},
     "output_type": "execute_result"
    }
   ],
   "source": [
    "test.__defaults__"
   ]
  },
  {
   "cell_type": "code",
   "execution_count": 14,
   "metadata": {},
   "outputs": [
    {
     "name": "stdout",
     "output_type": "stream",
     "text": [
      "1235 1234\n"
     ]
    }
   ],
   "source": [
    "test.__defaults__ = (1234,)\n",
    "test(1)"
   ]
  },
  {
   "cell_type": "code",
   "execution_count": 13,
   "metadata": {},
   "outputs": [
    {
     "data": {
      "text/plain": [
       "{'abn': 'sd'}"
      ]
     },
     "execution_count": 13,
     "metadata": {},
     "output_type": "execute_result"
    }
   ],
   "source": [
    "test.abn = 'sd'\n",
    "test.__dict__"
   ]
  },
  {
   "cell_type": "markdown",
   "metadata": {},
   "source": [
    "def实际上是运行期指令，以代码对象为参数，创建函数实例，并在当前上下文中与指定的名字相关联。"
   ]
  }
 ],
 "metadata": {
  "kernelspec": {
   "display_name": "Python 3",
   "language": "python",
   "name": "python3"
  },
  "language_info": {
   "codemirror_mode": {
    "name": "ipython",
    "version": 3
   },
   "file_extension": ".py",
   "mimetype": "text/x-python",
   "name": "python",
   "nbconvert_exporter": "python",
   "pygments_lexer": "ipython3",
   "version": "3.6.5"
  }
 },
 "nbformat": 4,
 "nbformat_minor": 2
}
