{
 "cells": [
  {
   "cell_type": "markdown",
   "metadata": {},
   "source": [
    "函数就像机械加工，着重于处理过程；类则关注数据本身，使其“活”过来。  \n",
    "类存在两种关系：继承(inhertiance)自某个族类，组合(composition)了哪些部件。   \n",
    "建议将类与业务逻辑分离。逻辑代表业务处理过程，其通常被设计为无状态，用上下文传递数据。业务逻辑讲究效率和并发性，以及相对固定的执行过程。逻辑适合以函数分段实现，按特定顺序组装，并以模块存储。这些特点都不适合以数据为核心，且注重家族遗传，用多实例体现个性的类来实现。"
   ]
  },
  {
   "cell_type": "code",
   "execution_count": 1,
   "metadata": {},
   "outputs": [],
   "source": [
    "def test():\n",
    "    class X:\n",
    "        data =100\n",
    "        def get(self):\n",
    "            return self.data\n"
   ]
  },
  {
   "cell_type": "code",
   "execution_count": 2,
   "metadata": {},
   "outputs": [
    {
     "name": "stdout",
     "output_type": "stream",
     "text": [
      "  2           0 LOAD_BUILD_CLASS\n",
      "              2 LOAD_CONST               1 (<code object X at 0x111a47540, file \"<ipython-input-1-47c898501eae>\", line 2>)\n",
      "              4 LOAD_CONST               2 ('X')\n",
      "              6 MAKE_FUNCTION            0\n",
      "              8 LOAD_CONST               2 ('X')\n",
      "             10 CALL_FUNCTION            2\n",
      "             12 STORE_FAST               0 (X)\n",
      "             14 LOAD_CONST               0 (None)\n",
      "             16 RETURN_VALUE\n"
     ]
    }
   ],
   "source": [
    "import dis\n",
    "dis.dis(test)"
   ]
  },
  {
   "cell_type": "markdown",
   "metadata": {},
   "source": [
    "先创建了X函数，其内容是属性设置和方法创建。随后该函数被当作参数传递给buildins.\\_\\_build_class__调用，这里其实就是元类在执行。"
   ]
  },
  {
   "cell_type": "code",
   "execution_count": 4,
   "metadata": {},
   "outputs": [
    {
     "name": "stdout",
     "output_type": "stream",
     "text": [
      "  2           0 LOAD_NAME                0 (__name__)\n",
      "              2 STORE_NAME               1 (__module__)\n",
      "              4 LOAD_CONST               0 ('test.<locals>.X')\n",
      "              6 STORE_NAME               2 (__qualname__)\n",
      "\n",
      "  3           8 LOAD_CONST               1 (100)\n",
      "             10 STORE_NAME               3 (data)\n",
      "\n",
      "  4          12 LOAD_CONST               2 (<code object get at 0x111a47c90, file \"<ipython-input-1-47c898501eae>\", line 4>)\n",
      "             14 LOAD_CONST               3 ('test.<locals>.X.get')\n",
      "             16 MAKE_FUNCTION            0\n",
      "             18 STORE_NAME               4 (get)\n",
      "             20 LOAD_CONST               4 (None)\n",
      "             22 RETURN_VALUE\n"
     ]
    }
   ],
   "source": [
    "dis.dis(test.__code__.co_consts[1])"
   ]
  },
  {
   "cell_type": "code",
   "execution_count": null,
   "metadata": {},
   "outputs": [],
   "source": []
  }
 ],
 "metadata": {
  "kernelspec": {
   "display_name": "Python 3",
   "language": "python",
   "name": "python3"
  },
  "language_info": {
   "codemirror_mode": {
    "name": "ipython",
    "version": 3
   },
   "file_extension": ".py",
   "mimetype": "text/x-python",
   "name": "python",
   "nbconvert_exporter": "python",
   "pygments_lexer": "ipython3",
   "version": "3.6.4"
  }
 },
 "nbformat": 4,
 "nbformat_minor": 2
}
